.travis.yml
MANIFEST.in
README.md
odpdown
odpdown.py
setup.cfg
setup.py
test.py
tox.ini
cramtest/minimal-usage.t
cramtest/nested-calls-page-interleave.t
cramtest/stdin-use.t
cramtest/test.md
cramtest/test.odp
cramtest/test.svg
cramtest/test.svg?_-\;^?!"$:%&=*+#test
cramtest/wrong-masterpages.t
odpdown.egg-info/PKG-INFO
odpdown.egg-info/SOURCES.txt
odpdown.egg-info/dependency_links.txt
odpdown.egg-info/requires.txt
odpdown.egg-info/top_level.txt