Metadata-Version: 1.1
Name: odpdown
Version: 0.4.0
Summary: Generate OpenDocument Presentation (odp) files from markdown
Home-page: https://github.com/thorstenb/odpdown.git
Author: Thorsten Behrens
Author-email: tbehrens@acm.org
License: BSD License
Platform: UNKNOWN
Classifier: Development Status :: 4 - Beta
Classifier: Environment :: Console
Classifier: Intended Audience :: End Users/Desktop
Classifier: Intended Audience :: Developers
Classifier: License :: OSI Approved :: BSD License
Classifier: Programming Language :: Python
Classifier: Topic :: Multimedia :: Graphics :: Presentation
Classifier: Topic :: Software Development :: Documentation
Classifier: Topic :: Office/Business
